ipdetective.py
ipdetective-1.0.2.dist-info/LICENSE
ipdetective-1.0.2.dist-info/METADATA
ipdetective-1.0.2.dist-info/WHEEL
ipdetective-1.0.2.dist-info/top_level.txt
ipdetective-1.0.2.dist-info/RECORD
