Metadata-Version: 2.1
Name: ipdetective
Version: 1.0.2
Summary: A Python client for IPDetective API
Author: IPDetective
Author-email: andrew@ipdetective.io
Project-URL: Homepage, https://ipdetective.io
Project-URL: Source, https://github.com/AndrewCopeland/ipdetective-client-python
Classifier: Programming Language :: Python :: 3
Classifier: License :: OSI Approved :: MIT License
Classifier: Operating System :: OS Independent
Classifier: Topic :: Software Development
Classifier: Topic :: Internet :: WWW/HTTP
Classifier: Topic :: Utilities
Classifier: Intended Audience :: Developers
License-File: LICENSE
Requires-Dist: requests
